setup.py
technologycycle/__init__.py
technologycycle/zhouqi.py
technologycycle.egg-info/PKG-INFO
technologycycle.egg-info/SOURCES.txt
technologycycle.egg-info/dependency_links.txt
technologycycle.egg-info/requires.txt
technologycycle.egg-info/top_level.txt