Metadata-Version: 1.1
Name: technologycycle
Version: 1.0.2
Summary: a tool for patent trend analysis
Home-page: https://pypi.org/manage/projects/
Author: qqqq
Author-email: 1412187956@qq.com
License: MIT
Platform: UNKNOWN
Classifier: Development Status :: 3 - Alpha
Classifier: Environment :: Web Environment
Classifier: Intended Audience :: Developers
Classifier: License :: OSI Approved :: BSD License
Classifier: Operating System :: OS Independent
Classifier: Programming Language :: Python
